qrange/__init__.py
qrange/__main__.py
qrange/qrange.py
qrange-1.0.6.dist-info/METADATA
qrange-1.0.6.dist-info/WHEEL
qrange-1.0.6.dist-info/top_level.txt
qrange-1.0.6.dist-info/RECORD
