Metadata-Version: 2.1
Name: qrange
Version: 1.0.6
Summary: Working with ranges made simple
Home-page: https://github.com/Forfunckle/qrange
Author: Forfunckle
Author-email: cosminjames555@gmail.com
License: MIT
Platform: UNKNOWN
Classifier: License :: OSI Approved :: MIT License
Classifier: Programming Language :: Python :: 3
Classifier: Programming Language :: Python :: 3.7
